pymia/__init__.py
pymia/__version__.py
pymia/data/__init__.py
pymia/data/assembler.py
pymia/data/augmentation.py
pymia/data/conversion.py
pymia/data/definition.py
pymia/data/indexexpression.py
pymia/data/subjectfile.py
pymia/data/transformation.py
pymia/data/backends/__init__.py
pymia/data/backends/pytorch/__init__.py
pymia/data/backends/pytorch/dataset.py
pymia/data/backends/pytorch/sample.py
pymia/data/backends/tensorflow/__init__.py
pymia/data/backends/tensorflow/dataset.py
pymia/data/creation/__init__.py
pymia/data/creation/callback.py
pymia/data/creation/fileloader.py
pymia/data/creation/traverser.py
pymia/data/creation/writer.py
pymia/data/extraction/__init__.py
pymia/data/extraction/byte_converter.py
pymia/data/extraction/datasource.py
pymia/data/extraction/extractor.py
pymia/data/extraction/indexing.py
pymia/data/extraction/reader.py
pymia/data/extraction/selection.py
pymia/evaluation/__init__.py
pymia/evaluation/evaluator.py
pymia/evaluation/writer.py
pymia/evaluation/metric/__init__.py
pymia/evaluation/metric/base.py
pymia/evaluation/metric/categorical.py
pymia/evaluation/metric/continuous.py
pymia/evaluation/metric/metric.py
pymia/filtering/__init__.py
pymia/filtering/filter.py
pymia/filtering/misc.py
pymia/filtering/postprocessing.py
pymia/filtering/preprocessing.py
pymia/filtering/registration.py
test/test_filtering/__init__.py
test/test_filtering/test_misc.py
test/test_filtering/test_postprocessing.py
test/test_filtering/test_preprocessing.py
test/test_image/__init__.py
test/test_image/test_image.py
pymia-0.3.4.dist-info/LICENSE
pymia-0.3.4.dist-info/METADATA
pymia-0.3.4.dist-info/WHEEL
pymia-0.3.4.dist-info/top_level.txt
pymia-0.3.4.dist-info/RECORD
