Metadata-Version: 2.1
Name: pymia
Version: 0.3.4
Summary: A Python package for data handling and evaluation in deep learning-based medical image analysis.
Home-page: https://pymia.readthedocs.io/
Author: Fabian Balsiger and Alain Jungo
Author-email: fabian.balsiger@insel.ch
License: Apache 2.0
Keywords: medical image analysis,deep learning,data handling,evaluation,metrics
Classifier: Development Status :: 3 - Alpha
Classifier: Intended Audience :: Developers
Classifier: Intended Audience :: Science/Research
Classifier: License :: OSI Approved :: Apache Software License
Classifier: Natural Language :: English
Classifier: Programming Language :: Python :: 3.6
Classifier: Topic :: Scientific/Engineering :: Image Recognition
Classifier: Topic :: Scientific/Engineering :: Mathematics
Classifier: Topic :: Scientific/Engineering :: Medical Science Apps.
Classifier: Topic :: Software Development :: Libraries :: Python Modules
Classifier: Topic :: Software Development :: Libraries
Requires-Python: >=3.6
License-File: LICENSE
Requires-Dist: h5py >=2.10.0
Requires-Dist: numpy >=1.12.1
Requires-Dist: scikit-image >=0.17.2
Requires-Dist: scipy >=1.3.2
Requires-Dist: SimpleITK >=1.2.3
